agilix_api_fr8train/__init__.py
agilix_api_fr8train/api.py
agilix_api_fr8train/factories/__init__.py
agilix_api_fr8train/factories/api.py
agilix_api_fr8train/factories/authentication.py
agilix_api_fr8train/factories/course.py
agilix_api_fr8train/factories/domain.py
agilix_api_fr8train/factories/enrollment.py
agilix_api_fr8train/factories/rights.py
agilix_api_fr8train/factories/submission.py
agilix_api_fr8train/factories/user.py
agilix_api_fr8train/models/__init__.py
agilix_api_fr8train/models/authentication.py
agilix_api_fr8train/models/connection.py
agilix_api_fr8train/models/courses.py
agilix_api_fr8train/models/datastreams.py
agilix_api_fr8train/models/domains.py
agilix_api_fr8train/models/enrollments.py
agilix_api_fr8train/models/generics.py
agilix_api_fr8train/models/manifests.py
agilix_api_fr8train/models/rights.py
agilix_api_fr8train/models/submissions.py
agilix_api_fr8train/models/users.py
agilix_api_fr8train-2.1.1.dist-info/licenses/LICENSE
agilix_api_fr8train-2.1.1.dist-info/METADATA
agilix_api_fr8train-2.1.1.dist-info/WHEEL
agilix_api_fr8train-2.1.1.dist-info/top_level.txt
agilix_api_fr8train-2.1.1.dist-info/RECORD
