Metadata-Version: 2.4
Name: agilix-api-fr8train
Version: 2.1.1
Summary: A Python SDK for integrating with the Agilix Buzz API
Author-email: Tyler Collette <tyler.collette@gmail.com>
Project-URL: Documentation, https://github.com/fr8train-sv/agilix-api/wiki
Project-URL: Source, https://github.com/fr8train-sv/agilix-api
Project-URL: Changelog, https://github.com/fr8train-sv/agilix-api/releases
Keywords: agilix,api,sdk,buzz,integration
Classifier: Programming Language :: Python :: 3
Classifier: Programming Language :: Python :: 3.12
Classifier: Operating System :: OS Independent
License-File: LICENSE
Requires-Dist: requests
Requires-Dist: dotenv
Requires-Dist: python-dotenv
Requires-Dist: pendulum
Dynamic: license-file
